{"go_index.md":"494a25a0","go_基础知识_map.md":"d48e28ec","go_基础知识_defer.md":"41b32a3a","go_基础知识_函数.md":"66f21865","go_基础知识_切片.md":"9a3dbc84","go_基础知识_包和文件.md":"1042f25a","go_基础知识_变量.md":"b8245a46","go_基础知识_基础数据类型.md":"07423319","go_基础知识_字符串.md":"2e265ed1","go_基础知识_常量.md":"64f15078","go_基础知识_循环语句.md":"22759998","go_基础知识_指针.md":"c33052b6","go_基础知识_数组.md":"9abcb5d4","go_基础知识_条件语句.md":"91da2b1b","go_基础知识_跳转语句.md":"9688eeb4","go_基础知识_选择语句.md":"bae2d683","go_进阶部分_协程.md":"d4736f95","go_进阶部分_接口.md":"2b40ec3a","go_进阶部分_结构体.md":"e37527fc","index.md":"f002f05c","java_index.md":"acadff39","java_观察者模式.md":"57f8c0a5","python_index.md":"24a28374","whisper_秦岭东坪沟草甸.md":"e9813dff","whisper_青海之行.md":"a7811de2"}
