{"go_index.md":"ceeacc84","go_基础知识_map.md":"d477409e","go_基础知识_defer.md":"e9eb478c","go_基础知识_函数.md":"c5543ee6","go_基础知识_切片.md":"7c7efc67","go_基础知识_包和文件.md":"64679e3b","go_基础知识_变量.md":"42015a5c","go_基础知识_基础数据类型.md":"d2ea489e","go_基础知识_字符串.md":"e500da51","go_基础知识_常量.md":"bbbf5a38","go_基础知识_循环语句.md":"229bef39","go_基础知识_指针.md":"170c9bce","go_基础知识_数组.md":"faad6b5e","go_基础知识_条件语句.md":"bd32cd77","go_基础知识_跳转语句.md":"5dddd332","go_基础知识_选择语句.md":"6cf89855","go_进阶部分_协程.md":"2e596238","go_进阶部分_接口.md":"3823a70b","go_进阶部分_结构体.md":"9607d765","index.md":"ec040642","java_index.md":"7c7df1fe","python_index.md":"670c8950","whisper_秦岭东坪沟草甸.md":"4f7bd682","whisper_青海之行.md":"9d7ea293"}
